seuils/__init__.py
seuils/figures.py
seuils/pages.py
seuils/usure.py
seuils/data/avis.json
seuils/data/seuils.json
seuils/pdf/2005-01-01.pdf
seuils/pdf/2005-04-01.pdf
seuils/pdf/2005-07-01.pdf
seuils/pdf/2005-10-01.pdf
seuils/pdf/2006-01-01.pdf
seuils/pdf/2006-04-01.pdf
seuils/pdf/2006-07-01.pdf
seuils/pdf/2006-10-01.pdf
seuils/pdf/2007-01-01.pdf
seuils/pdf/2007-04-01.pdf
seuils/pdf/2007-07-01.pdf
seuils/pdf/2007-10-01.pdf
seuils/pdf/2008-01-01.pdf
seuils/pdf/2008-04-01.pdf
seuils/pdf/2008-07-01.pdf
seuils/pdf/2008-10-01.pdf
seuils/pdf/2009-01-01.pdf
seuils/pdf/2009-04-01.pdf
seuils/pdf/2009-07-01.pdf
seuils/pdf/2009-10-01.pdf
seuils/pdf/2010-01-01.pdf
seuils/pdf/2010-04-01.pdf
seuils/pdf/2010-07-01.pdf
seuils/pdf/2010-10-01.pdf
seuils/pdf/2011-01-01.pdf
seuils/pdf/2011-04-01.pdf
seuils/pdf/2011-07-01.pdf
seuils/pdf/2011-10-01.pdf
seuils/pdf/2012-01-01.pdf
seuils/pdf/2012-04-01.pdf
seuils/pdf/2012-07-01.pdf
seuils/pdf/2012-10-01.pdf
seuils/pdf/2013-01-01.pdf
seuils/pdf/2013-04-01.pdf
seuils/pdf/2013-07-01.pdf
seuils/pdf/2013-10-01.pdf
seuils/pdf/2014-01-01.pdf
seuils/pdf/2014-04-01.pdf
seuils/pdf/2014-07-01.pdf
seuils/pdf/2014-10-01.pdf
seuils/pdf/2015-01-01.pdf
seuils/pdf/2015-04-01.pdf
seuils/pdf/2015-07-01.pdf
seuils/pdf/2015-10-01.pdf
seuils/pdf/2016-01-01.pdf
seuils/pdf/2016-04-01.pdf
seuils/pdf/2016-07-01.pdf
seuils/pdf/2016-10-01.pdf
seuils/pdf/2017-01-01.pdf
seuils/pdf/2017-04-01.pdf
seuils/pdf/2017-07-01.pdf
seuils/pdf/2017-10-01.pdf
seuils/pdf/2018-01-01.pdf
seuils/pdf/2018-04-01.pdf
seuils/pdf/2018-07-01.pdf
seuils/pdf/2018-10-01.pdf
seuils/pdf/2019-01-01.pdf
seuils/pdf/2019-04-01.pdf
seuils/pdf/2019-07-01.pdf
seuils/pdf/2019-10-01.pdf
seuils/pdf/2020-01-01.pdf
seuils/pdf/2020-04-01.pdf
seuils/pdf/2020-07-01.pdf
seuils/pdf/2020-10-01.pdf
seuils/pdf/2021-01-01.pdf
seuils/pdf/2021-04-01.pdf
seuils/pdf/2021-07-01.pdf
seuils/pdf/2021-10-01.pdf
seuils/pdf/2022-01-01.pdf
seuils/pdf/2022-04-01.pdf
seuils/pdf/2022-07-01.pdf
seuils/pdf/2022-10-01.pdf
seuils-2026.1.0.dist-info/METADATA
seuils-2026.1.0.dist-info/WHEEL
seuils-2026.1.0.dist-info/top_level.txt
seuils-2026.1.0.dist-info/RECORD
