Metadata-Version: 2.4
Name: seuils
Version: 2026.1.0
Summary: Répertoire des seuils de l'usure en vigueur en France depuis 2005
Author-email: Thibaut_S <git@outils-jcp.fr>
Project-URL: Homepage, https://gitlab.com/outils-jcp/seuils-usure
Project-URL: Bug Tracker, https://gitlab.com/outils-jcp/seuils-usure/-/issues
Keywords: usure,seuils de l'usure,taux,taeg,credit
Requires-Python: >=3.8
Requires-Dist: fr-date
Requires-Dist: requests
Provides-Extra: dev
Requires-Dist: ruff; extra == "dev"
Requires-Dist: black; extra == "dev"
Requires-Dist: pip-tools; extra == "dev"
Requires-Dist: pytest; extra == "dev"
Requires-Dist: pandas; extra == "dev"
Requires-Dist: plotly; extra == "dev"
Requires-Dist: jinja2; extra == "dev"
